rapidqcms/AcquisitionListener.py
rapidqcms/AutoQCProcessing.py
rapidqcms/DashWebApp.py
rapidqcms/DatabaseFunctions.py
rapidqcms/PlotGeneration.py
rapidqcms/SlackNotifications.py
rapidqcms/__init__.py
rapidqcms/__main__.py
rapidqcms/assets/favicon.ico
rapidqcms/assets/styles.css
rapid_qc_ms-1.1.0.dist-info/METADATA
rapid_qc_ms-1.1.0.dist-info/WHEEL
rapid_qc_ms-1.1.0.dist-info/entry_points.txt
rapid_qc_ms-1.1.0.dist-info/top_level.txt
rapid_qc_ms-1.1.0.dist-info/RECORD
